oss_cleaner/__init__.py
oss_cleaner/__main__.py
oss_cleaner/_version.py
oss_cleaner/app.py
oss_cleaner/config_manager.py
oss_cleaner/templates/index.html
oss_cleaner-0.1.2.dist-info/METADATA
oss_cleaner-0.1.2.dist-info/WHEEL
oss_cleaner-0.1.2.dist-info/licenses/LICENSE
oss_cleaner-0.1.2.dist-info/RECORD
