Metadata-Version: 2.4
Name: oss-cleaner
Version: 0.1.2
Summary: Manage and clean orphaned images stored in Aliyun OSS for Markdown projects.
License-File: LICENSE
Requires-Python: >=3.8
Requires-Dist: flask>=2.3
Requires-Dist: oss2>=2.18
